[
  { "id": 1, "text": "Apakah konsep perkahwinan bagi anda?", "tags": ["Perkahwinan", "Nilai"] },
  { "id": 2, "text": "Adakah anda pernah berkahwin sebelum ini?", "tags": ["Perkahwinan", "Sejarah"] },
  { "id": 3, "text": "Adakah anda sudah berkahwin sekarang?", "tags": ["Perkahwinan", "Status"] },
  { "id": 4, "text": "Apakah harapan anda terhadap perkahwinan?", "tags": ["Perkahwinan", "Harapan"] },
  { "id": 5, "text": "Apakah matlamat hidup anda? Rancangan jangka panjang dan jangka pendek.", "tags": ["Gaya Hidup", "Matlamat"] },
  { "id": 6, "text": "Nyatakan tiga perkara yang anda ingin capai dalam masa terdekat.", "tags": ["Gaya Hidup", "Matlamat"] },
  { "id": 7, "text": "Nyatakan tiga perkara yang anda ingin capai dalam jangka masa panjang.", "tags": ["Gaya Hidup", "Matlamat"] },
  { "id": 8, "text": "Mengapa anda memilih saya sebagai bakal pasangan anda?", "tags": ["Perkahwinan", "Peribadi"] },
  { "id": 9, "text": "Apakah peranan agama dalam hidup anda sekarang?", "tags": ["Agama", "Peribadi"] },
  { "id": 10, "text": "Adakah anda seorang yang spiritual?", "tags": ["Agama", "Peribadi"] },
  { "id": 11, "text": "Apakah pemahaman anda tentang perkahwinan Islam?", "tags": ["Agama", "Perkahwinan"] },
  { "id": 12, "text": "Apakah yang anda harapkan daripada pasangan anda dari segi agama?", "tags": ["Agama", "Harapan"] },
  { "id": 13, "text": "Bagaimana hubungan anda dengan komuniti Muslim di kawasan anda?", "tags": ["Agama", "Komuniti"] },
  { "id": 14, "text": "Adakah anda terlibat dalam aktiviti sukarelawan Islam?", "tags": ["Agama", "Komuniti"] },
  { "id": 15, "text": "Apa yang boleh anda tawarkan kepada pasangan anda dari segi kerohanian?", "tags": ["Agama", "Perkongsian"] },
  { "id": 16, "text": "Apakah peranan seorang suami?", "tags": ["Perkahwinan", "Peranan"] },
  { "id": 17, "text": "Apakah peranan seorang isteri?", "tags": ["Perkahwinan", "Peranan"] },
  { "id": 18, "text": "Adakah anda ingin mengamalkan poligami?", "tags": ["Perkahwinan", "Agama"] },
  { "id": 19, "text": "Bagaimana hubungan anda dengan keluarga anda?", "tags": ["Keluarga", "Hubungan"] },
  { "id": 20, "text": "Bagaimana anda mengharapkan hubungan anda dengan keluarga pasangan anda?", "tags": ["Keluarga", "Harapan"] },
  { "id": 21, "text": "Bagaimana anda mengharapkan hubungan antara pasangan anda dan keluarga anda?", "tags": ["Keluarga", "Harapan"] },
  { "id": 22, "text": "Adakah terdapat ahli keluarga anda yang tinggal bersama anda sekarang?", "tags": ["Keluarga", "Kediaman"] },
  { "id": 23, "text": "Adakah anda merancang untuk membenarkan ahli keluarga tinggal bersama anda pada masa hadapan?", "tags": ["Keluarga", "Kediaman"] },
  { "id": 24, "text": "Jika hubungan saya dengan keluarga anda menjadi tegang, apa yang patut dilakukan?", "tags": ["Keluarga", "Penyelesaian Konflik"] },
  { "id": 25, "text": "Siapakah kawan-kawan anda? Nyatakan sekurang-kurangnya tiga orang.", "tags": ["Kawan", "Hubungan"] },
  { "id": 26, "text": "Bagaimana anda mengenali mereka?", "tags": ["Kawan", "Hubungan"] },
  { "id": 27, "text": "Mengapa mereka menjadi kawan anda?", "tags": ["Kawan", "Nilai"] },
  { "id": 28, "text": "Apa yang anda paling suka tentang mereka?", "tags": ["Kawan", "Nilai"] },
  { "id": 29, "text": "Bagaimana hubungan anda dengan mereka selepas berkahwin?", "tags": ["Kawan", "Perkahwinan"] },
  { "id": 30, "text": "Adakah anda mempunyai kawan berlainan jantina?", "tags": ["Kawan", "Batasan"] },
  { "id": 31, "text": "Apakah tahap hubungan anda dengan mereka sekarang?", "tags": ["Kawan", "Batasan"] },
  { "id": 32, "text": "Bagaimana tahap hubungan anda dengan mereka selepas berkahwin?", "tags": ["Kawan", "Perkahwinan"] },
  { "id": 33, "text": "Bagaimana hubungan yang anda inginkan antara pasangan anda dan kawan-kawan anda?", "tags": ["Kawan", "Harapan"] },
  { "id": 34, "text": "Apakah aktiviti yang anda lakukan pada masa lapang?", "tags": ["Gaya Hidup", "Hobi"] },
  { "id": 35, "text": "Adakah anda suka menjemput tetamu ke rumah untuk hiburan?", "tags": ["Gaya Hidup", "Sosial"] },
  { "id": 36, "text": "Apakah yang anda harapkan daripada pasangan anda apabila kawan-kawan anda datang ke rumah?", "tags": ["Kawan", "Harapan"] },
  { "id": 37, "text": "Apakah pendapat anda tentang bercakap dalam bahasa lain di rumah yang saya tidak faham? Dengan kawan? Dengan keluarga?", "tags": ["Komunikasi", "Budaya"] },
  { "id": 38, "text": "Adakah anda suka melancong?", "tags": ["Gaya Hidup", "Pelancongan"] },
  { "id": 39, "text": "Bagaimana anda menghabiskan masa cuti anda?", "tags": ["Gaya Hidup", "Pelancongan"] },
  { "id": 40, "text": "Bagaimana anda fikir pasangan anda patut menghabiskan masa cuti?", "tags": ["Gaya Hidup", "Harapan"] },
  { "id": 41, "text": "Adakah anda suka membaca?", "tags": ["Gaya Hidup", "Pendidikan"] },
  { "id": 42, "text": "Apa yang anda baca?", "tags": ["Gaya Hidup", "Pendidikan"] },
  { "id": 43, "text": "Selepas berkahwin, adakah anda akan meluahkan perasaan romantik secara lisan?", "tags": ["Komunikasi", "Romantik"] },
  { "id": 44, "text": "Selepas berkahwin, adakah anda ingin menunjukkan kasih sayang di khalayak ramai?", "tags": ["Komunikasi", "Romantik"] },
  { "id": 45, "text": "Bagaimana anda menunjukkan kekaguman kepada seseorang yang anda kenali sekarang?", "tags": ["Komunikasi", "Peribadi"] },
  { "id": 46, "text": "Bagaimana anda meluahkan perasaan kepada seseorang yang telah membantu anda?", "tags": ["Komunikasi", "Kesyukuran"] },
  { "id": 47, "text": "Adakah anda suka menulis perasaan anda?", "tags": ["Komunikasi", "Peribadi"] },
  { "id": 48, "text": "Jika anda bersalah kepada seseorang, bagaimana anda memohon maaf?", "tags": ["Komunikasi", "Penyelesaian Konflik"] },
  { "id": 49, "text": "Jika seseorang bersalah kepada anda, bagaimana anda mahu mereka memohon maaf kepada anda?", "tags": ["Komunikasi", "Penyelesaian Konflik"] },
  { "id": 50, "text": "Berapa lama masa yang anda perlukan sebelum memaafkan seseorang?", "tags": ["Komunikasi", "Kemaafan"] },
  { "id": 51, "text": "Bagaimana anda membuat keputusan penting dan kurang penting dalam hidup anda?", "tags": ["Komunikasi", "Pembuatan Keputusan"] },
  { "id": 52, "text": "Adakah anda menggunakan bahasa kasar di rumah? Di tempat awam? Dengan keluarga anda?", "tags": ["Komunikasi", "Nilai"] },
  { "id": 53, "text": "Adakah kawan-kawan anda menggunakan bahasa kasar?", "tags": ["Kawan", "Nilai"] },
  { "id": 54, "text": "Adakah keluarga anda menggunakan bahasa kasar?", "tags": ["Keluarga", "Nilai"] },
  { "id": 55, "text": "Bagaimana anda meluahkan kemarahan?", "tags": ["Komunikasi", "Penyelesaian Konflik"] },
  { "id": 56, "text": "Bagaimana anda mengharapkan pasangan anda meluahkan kemarahan?", "tags": ["Komunikasi", "Harapan"] },
  { "id": 57, "text": "Apa yang anda lakukan apabila anda marah?", "tags": ["Komunikasi", "Penyelesaian Konflik"] },
  { "id": 58, "text": "Bilakah anda rasa sesuai untuk memulakan mediasi dalam perkahwinan?", "tags": ["Perkahwinan", "Penyelesaian Konflik"] },
  { "id": 59, "text": "Jika berlaku pertikaian dalam perkahwinan anda, agama atau tidak, bagaimana konflik itu patut diselesaikan?", "tags": ["Perkahwinan", "Penyelesaian Konflik"] },
  { "id": 60, "text": "Jelaskan penderaan mental, lisan, emosi, dan fizikal.", "tags": ["Keselamatan", "Kesedaran"] },
  { "id": 61, "text": "Apa yang anda akan lakukan jika anda rasa anda telah didera?", "tags": ["Keselamatan", "Tindakan"] },
  { "id": 62, "text": "Siapa yang akan anda hubungi untuk bantuan jika anda didera?", "tags": ["Keselamatan", "Sokongan"] },
  { "id": 63, "text": "Adakah anda menghidap sebarang penyakit atau keadaan kronik?", "tags": ["Kesihatan", "Perubatan"] },
  { "id": 64, "text": "Adakah anda sanggup menjalani pemeriksaan kesihatan oleh doktor sebelum berkahwin?", "tags": ["Kesihatan", "Perkahwinan"] },
  { "id": 65, "text": "Apakah pemahaman anda tentang kesihatan dan pemakanan yang baik?", "tags": ["Kesihatan", "Gaya Hidup"] },
  { "id": 66, "text": "Bagaimana anda menjaga kesihatan dan pemakanan anda sendiri?", "tags": ["Kesihatan", "Gaya Hidup"] },
  { "id": 67, "text": "Apakah definisi kekayaan bagi anda?", "tags": ["Kewangan", "Nilai"] },
  { "id": 68, "text": "Bagaimana anda membelanjakan wang anda?", "tags": ["Kewangan", "Tabiat"] },
  { "id": 69, "text": "Bagaimana anda menyimpan wang anda?", "tags": ["Kewangan", "Tabiat"] },
  { "id": 70, "text": "Bagaimana anda fikir penggunaan wang anda akan berubah selepas berkahwin?", "tags": ["Kewangan", "Perkahwinan"] },
  { "id": 71, "text": "Adakah anda mempunyai hutang sekarang? Jika ya, bagaimana anda berusaha untuk melangsaikannya?", "tags": ["Kewangan", "Hutang"] },
  { "id": 72, "text": "Adakah anda menggunakan kad kredit?", "tags": ["Kewangan", "Tabiat"] },
  { "id": 73, "text": "Adakah anda menyokong idea mengambil pinjaman untuk membeli rumah?", "tags": ["Kewangan", "Pelaburan"] },
  { "id": 74, "text": "Apakah yang anda harapkan daripada pasangan anda dari segi kewangan?", "tags": ["Kewangan", "Harapan"] },
  { "id": 75, "text": "Apakah tanggungjawab kewangan anda dalam perkahwinan?", "tags": ["Kewangan", "Perkahwinan"] },
  { "id": 76, "text": "Adakah anda menyokong idea isteri bekerja?", "tags": ["Kewangan", "Peranan"] },
  { "id": 77, "text": "Jika ya, bagaimana anda fikir keluarga dua pendapatan patut menguruskan kewangan?", "tags": ["Kewangan", "Perkahwinan"] },
  { "id": 78, "text": "Adakah anda menggunakan bajet untuk menguruskan kewangan anda sekarang?", "tags": ["Kewangan", "Perancangan"] },
  { "id": 79, "text": "Siapakah individu yang anda bertanggungjawab dari segi kewangan?", "tags": ["Kewangan", "Tanggungjawab"] },
  { "id": 80, "text": "Adakah anda menyokong penggunaan pengasuh dan pembantu rumah?", "tags": ["Gaya Hidup", "Bantuan"] },
  { "id": 81, "text": "Adakah anda ingin mempunyai anak? Jika tidak, mengapa?", "tags": ["Anak", "Perancangan"] },
  { "id": 82, "text": "Pada pengetahuan anda, adakah anda mampu untuk mempunyai anak?", "tags": ["Anak", "Kesihatan"] },
  { "id": 83, "text": "Adakah anda ingin mempunyai anak dalam dua tahun pertama perkahwinan? Jika tidak, bila?", "tags": ["Anak", "Garis Masa"] },
  { "id": 84, "text": "Adakah anda percaya kepada pengguguran dalam keluarga anda?", "tags": ["Anak", "Nilai"] },
  { "id": 85, "text": "Adakah anda sudah mempunyai anak sekarang?", "tags": ["Anak", "Status"] },
  { "id": 86, "text": "Bagaimana hubungan anda dengan anak-anak anda sekarang?", "tags": ["Anak", "Hubungan"] },
  { "id": 87, "text": "Bagaimana hubungan anda dengan ibu atau bapa kepada anak-anak anda sekarang?", "tags": ["Anak", "Ibu Bapa Bersama"] },
  { "id": 88, "text": "Bagaimana hubungan yang anda harapkan antara pasangan anda dengan anak-anak anda dan ibu/bapa mereka?", "tags": ["Anak", "Harapan"] },
  { "id": 89, "text": "Apakah kaedah terbaik untuk membesarkan anak-anak?", "tags": ["Anak", "Keibubapaan"] },
  { "id": 90, "text": "Apakah kaedah terbaik untuk mendisiplinkan anak-anak?", "tags": ["Anak", "Disiplin"] },
  { "id": 91, "text": "Bagaimana anda dibesarkan?", "tags": ["Anak", "Sejarah Peribadi"] },
  { "id": 92, "text": "Bagaimana anda didisiplinkan?", "tags": ["Anak", "Sejarah Peribadi"] },
  { "id": 93, "text": "Adakah anda percaya kepada rotan anak-anak? Dalam keadaan bagaimana?", "tags": ["Anak", "Disiplin"] },
  { "id": 94, "text": "Adakah anda percaya kepada sekolah awam untuk anak-anak anda?", "tags": ["Anak", "Pendidikan"] },
  { "id": 95, "text": "Adakah anda percaya kepada sekolah Islam untuk anak-anak anda?", "tags": ["Anak", "Pendidikan", "Agama"] },
  { "id": 96, "text": "Adakah anda percaya kepada pembelajaran di rumah untuk anak-anak anda? Jika ya, oleh siapa?", "tags": ["Anak", "Pendidikan"] },
  { "id": 97, "text": "Bagaimana hubungan yang sepatutnya antara anak-anak anda dengan rakan sekelas dan kawan bukan Muslim?", "tags": ["Anak", "Agama", "Sosial"] },
  { "id": 98, "text": "Adakah anda akan menghantar anak-anak anda melawat keluarga besar mereka jika mereka tinggal di negeri atau negara lain?", "tags": ["Anak", "Keluarga", "Pelancongan"] },
  { "id": 99, "text": "Bagaimana hubungan yang anda inginkan antara anak-anak anda dengan semua datuk dan nenek mereka?", "tags": ["Anak", "Keluarga"] },
  { "id": 100, "text": "Jika ada ahli keluarga saya yang bukan Muslim, berlainan budaya atau bangsa, bagaimana hubungan yang anda inginkan dengan mereka?", "tags": ["Keluarga", "Agama", "Budaya"] }
] 